{"scoring_key": "bind_gemma3_12b", "samples": [{"ask_first": false, "bare": 11.6875, "neutral": 12.0, "strip_ord": 9.4375, "strip_shuf": 8.0, "retain_ord": 5.6875}, {"ask_first": true, "bare": 14.1875, "neutral": 13.9375, "strip_ord": 12.0625, "strip_shuf": 12.625, "retain_ord": 5.0}, {"ask_first": false, "bare": 22.25, "neutral": 23.25, "strip_ord": 24.625, "strip_shuf": 23.375, "retain_ord": 8.6875}, {"ask_first": true, "bare": 25.0, "neutral": 26.625, "strip_ord": 20.0, "strip_shuf": 17.625, "retain_ord": 8.8125}, {"ask_first": false, "bare": 24.5, "neutral": 25.625, "strip_ord": 25.625, "strip_shuf": 23.375, "retain_ord": 6.28125}, {"ask_first": false, "bare": 13.875, "neutral": 14.625, "strip_ord": 13.875, "strip_shuf": 12.75, "retain_ord": 4.6875}, {"ask_first": true, "bare": 25.0, "neutral": 27.5, "strip_ord": 18.0, "strip_shuf": 15.1875, "retain_ord": 14.0}, {"ask_first": false, "bare": 24.75, "neutral": 26.125, "strip_ord": 33.0, "strip_shuf": 29.125, "retain_ord": 8.0625}, {"ask_first": false, "bare": 12.4375, "neutral": 12.125, "strip_ord": 10.3125, "strip_shuf": 12.0625, "retain_ord": 3.734375}, {"ask_first": true, "bare": 8.3125, "neutral": 9.5, "strip_ord": 7.53125, "strip_shuf": 10.75, "retain_ord": 2.890625}, {"ask_first": false, "bare": 11.0, "neutral": 10.9375, "strip_ord": 10.75, "strip_shuf": 11.375, "retain_ord": 4.90625}, {"ask_first": true, "bare": 14.625, "neutral": 14.375, "strip_ord": 11.1875, "strip_shuf": 11.5, "retain_ord": 4.65625}, {"ask_first": false, "bare": 21.125, "neutral": 21.375, "strip_ord": 20.5, "strip_shuf": 21.0, "retain_ord": 8.0625}, {"ask_first": true, "bare": 21.0, "neutral": 24.25, "strip_ord": 18.75, "strip_shuf": 15.0, "retain_ord": 9.25}, {"ask_first": true, "bare": 25.0, "neutral": 26.375, "strip_ord": 30.5, "strip_shuf": 27.625, "retain_ord": 7.09375}, {"ask_first": true, "bare": 8.625, "neutral": 7.59375, "strip_ord": 5.6875, "strip_shuf": 7.53125, "retain_ord": 3.546875}, {"ask_first": false, "bare": 24.25, "neutral": 24.75, "strip_ord": 23.75, "strip_shuf": 23.125, "retain_ord": 6.875}, {"ask_first": false, "bare": 26.875, "neutral": 28.0, "strip_ord": 29.125, "strip_shuf": 32.5, "retain_ord": 6.34375}, {"ask_first": false, "bare": 12.5, "neutral": 12.375, "strip_ord": 9.0625, "strip_shuf": 11.4375, "retain_ord": 3.390625}, {"ask_first": false, "bare": 12.0625, "neutral": 13.125, "strip_ord": 12.5625, "strip_shuf": 12.1875, "retain_ord": 4.6875}, {"ask_first": false, "bare": 11.5625, "neutral": 11.1875, "strip_ord": 12.25, "strip_shuf": 10.125, "retain_ord": 5.28125}, {"ask_first": false, "bare": 10.5, "neutral": 10.6875, "strip_ord": 10.6875, "strip_shuf": 8.4375, "retain_ord": 3.921875}, {"ask_first": true, "bare": 21.625, "neutral": 20.625, "strip_ord": 22.5, "strip_shuf": 23.0, "retain_ord": 5.40625}, {"ask_first": false, "bare": 9.9375, "neutral": 10.375, "strip_ord": 11.375, "strip_shuf": 9.1875, "retain_ord": 4.15625}, {"ask_first": false, "bare": 22.125, "neutral": 22.75, "strip_ord": 26.0, "strip_shuf": 17.125, "retain_ord": 9.375}, {"ask_first": false, "bare": 13.625, "neutral": 13.375, "strip_ord": 12.4375, "strip_shuf": 13.0, "retain_ord": 5.0625}, {"ask_first": false, "bare": 21.375, "neutral": 22.0, "strip_ord": 23.25, "strip_shuf": 18.75, "retain_ord": 6.25}, {"ask_first": false, "bare": 25.25, "neutral": 25.5, "strip_ord": 27.625, "strip_shuf": 20.75, "retain_ord": 7.3125}, {"ask_first": true, "bare": 8.3125, "neutral": 9.9375, "strip_ord": 6.96875, "strip_shuf": 7.15625, "retain_ord": 2.734375}, {"ask_first": true, "bare": 8.375, "neutral": 8.5625, "strip_ord": 8.375, "strip_shuf": 7.96875, "retain_ord": 4.15625}, {"ask_first": false, "bare": 10.5, "neutral": 12.8125, "strip_ord": 8.0, "strip_shuf": 10.1875, "retain_ord": 6.75}, {"ask_first": false, "bare": 10.0625, "neutral": 9.5, "strip_ord": 8.0625, "strip_shuf": 9.0625, "retain_ord": 4.5625}, {"ask_first": false, "bare": 22.875, "neutral": 22.625, "strip_ord": 23.25, "strip_shuf": 16.0, "retain_ord": 6.21875}, {"ask_first": false, "bare": 9.8125, "neutral": 9.1875, "strip_ord": 10.75, "strip_shuf": 6.4375, "retain_ord": 3.359375}, {"ask_first": true, "bare": 21.5, "neutral": 23.875, "strip_ord": 23.125, "strip_shuf": 19.0, "retain_ord": 6.71875}, {"ask_first": false, "bare": 13.625, "neutral": 14.375, "strip_ord": 13.625, "strip_shuf": 11.9375, "retain_ord": 4.75}, {"ask_first": true, "bare": 22.125, "neutral": 25.25, "strip_ord": 21.125, "strip_shuf": 17.875, "retain_ord": 11.0625}, {"ask_first": false, "bare": 27.25, "neutral": 26.625, "strip_ord": 29.25, "strip_shuf": 24.5, "retain_ord": 8.0}, {"ask_first": true, "bare": 10.3125, "neutral": 10.875, "strip_ord": 8.3125, "strip_shuf": 8.5, "retain_ord": 3.8125}, {"ask_first": false, "bare": 10.4375, "neutral": 10.9375, "strip_ord": 9.3125, "strip_shuf": 5.53125, "retain_ord": 4.59375}, {"ask_first": true, "bare": 21.25, "neutral": 19.625, "strip_ord": 16.375, "strip_shuf": 18.0, "retain_ord": 8.1875}, {"ask_first": true, "bare": 14.0, "neutral": 10.625, "strip_ord": 11.0, "strip_shuf": 6.75, "retain_ord": 5.25}, {"ask_first": false, "bare": 23.25, "neutral": 23.875, "strip_ord": 25.5, "strip_shuf": 20.125, "retain_ord": 7.5}, {"ask_first": false, "bare": 12.6875, "neutral": 11.75, "strip_ord": 11.375, "strip_shuf": 11.0, "retain_ord": 3.9375}, {"ask_first": true, "bare": 31.625, "neutral": 30.5, "strip_ord": 25.25, "strip_shuf": 18.625, "retain_ord": 8.6875}, {"ask_first": true, "bare": 10.125, "neutral": 10.125, "strip_ord": 6.8125, "strip_shuf": 7.15625, "retain_ord": 3.9375}, {"ask_first": true, "bare": 30.25, "neutral": 26.125, "strip_ord": 27.0, "strip_shuf": 22.375, "retain_ord": 14.5}, {"ask_first": true, "bare": 13.0625, "neutral": 13.0, "strip_ord": 9.5625, "strip_shuf": 14.4375, "retain_ord": 3.890625}, {"ask_first": false, "bare": 12.5, "neutral": 13.9375, "strip_ord": 13.75, "strip_shuf": 13.6875, "retain_ord": 4.78125}, {"ask_first": true, "bare": 8.0625, "neutral": 8.4375, "strip_ord": 8.875, "strip_shuf": 8.4375, "retain_ord": 3.828125}, {"ask_first": true, "bare": 22.0, "neutral": 22.25, "strip_ord": 23.875, "strip_shuf": 19.125, "retain_ord": 8.4375}, {"ask_first": false, "bare": 11.4375, "neutral": 12.0625, "strip_ord": 11.5, "strip_shuf": 12.25, "retain_ord": 2.734375}, {"ask_first": true, "bare": 18.375, "neutral": 21.75, "strip_ord": 21.5, "strip_shuf": 18.25, "retain_ord": 5.75}, {"ask_first": true, "bare": 25.25, "neutral": 25.375, "strip_ord": 22.0, "strip_shuf": 21.25, "retain_ord": 9.625}, {"ask_first": true, "bare": 25.25, "neutral": 25.75, "strip_ord": 23.25, "strip_shuf": 15.0625, "retain_ord": 7.5625}, {"ask_first": false, "bare": 14.0, "neutral": 14.625, "strip_ord": 12.8125, "strip_shuf": 14.5, "retain_ord": 4.8125}, {"ask_first": false, "bare": 20.625, "neutral": 19.625, "strip_ord": 25.0, "strip_shuf": 17.25, "retain_ord": 7.0625}, {"ask_first": true, "bare": 11.0625, "neutral": 11.625, "strip_ord": 5.65625, "strip_shuf": 3.96875, "retain_ord": 3.75}, {"ask_first": true, "bare": 9.875, "neutral": 10.5625, "strip_ord": 7.84375, "strip_shuf": 9.5, "retain_ord": 3.453125}, {"ask_first": true, "bare": 8.75, "neutral": 9.3125, "strip_ord": 8.4375, "strip_shuf": 6.71875, "retain_ord": 3.734375}, {"ask_first": true, "bare": 20.25, "neutral": 19.5, "strip_ord": 19.0, "strip_shuf": 19.0, "retain_ord": 8.8125}, {"ask_first": false, "bare": 10.25, "neutral": 10.125, "strip_ord": 9.8125, "strip_shuf": 8.625, "retain_ord": 4.46875}, {"ask_first": true, "bare": 20.5, "neutral": 19.75, "strip_ord": 21.375, "strip_shuf": 16.125, "retain_ord": 10.3125}, {"ask_first": false, "bare": 9.8125, "neutral": 9.5625, "strip_ord": 6.53125, "strip_shuf": 8.125, "retain_ord": 3.75}, {"ask_first": false, "bare": 19.625, "neutral": 20.5, "strip_ord": 21.875, "strip_shuf": 19.125, "retain_ord": 8.9375}, {"ask_first": true, "bare": 9.875, "neutral": 9.0, "strip_ord": 8.0, "strip_shuf": 4.84375, "retain_ord": 3.75}, {"ask_first": true, "bare": 21.75, "neutral": 19.25, "strip_ord": 22.0, "strip_shuf": 17.25, "retain_ord": 15.5625}, {"ask_first": false, "bare": 26.75, "neutral": 23.25, "strip_ord": 28.125, "strip_shuf": 21.25, "retain_ord": 7.96875}, {"ask_first": false, "bare": 12.25, "neutral": 12.6875, "strip_ord": 13.4375, "strip_shuf": 12.125, "retain_ord": 3.40625}, {"ask_first": true, "bare": 7.96875, "neutral": 8.5, "strip_ord": 8.8125, "strip_shuf": 8.375, "retain_ord": 3.765625}, {"ask_first": false, "bare": 11.625, "neutral": 10.4375, "strip_ord": 13.125, "strip_shuf": 12.75, "retain_ord": 5.125}, {"ask_first": true, "bare": 14.0625, "neutral": 12.0, "strip_ord": 12.1875, "strip_shuf": 11.75, "retain_ord": 5.0625}, {"ask_first": false, "bare": 22.875, "neutral": 23.625, "strip_ord": 21.75, "strip_shuf": 24.875, "retain_ord": 9.0}, {"ask_first": true, "bare": 22.875, "neutral": 22.875, "strip_ord": 20.125, "strip_shuf": 18.125, "retain_ord": 8.9375}, {"ask_first": false, "bare": 21.75, "neutral": 21.125, "strip_ord": 26.25, "strip_shuf": 13.6875, "retain_ord": 8.6875}, {"ask_first": true, "bare": 10.4375, "neutral": 10.9375, "strip_ord": 7.9375, "strip_shuf": 9.125, "retain_ord": 4.03125}, {"ask_first": false, "bare": 25.375, "neutral": 23.625, "strip_ord": 21.5, "strip_shuf": 22.75, "retain_ord": 9.375}, {"ask_first": false, "bare": 27.625, "neutral": 27.125, "strip_ord": 29.0, "strip_shuf": 27.25, "retain_ord": 9.5}, {"ask_first": false, "bare": 13.125, "neutral": 13.3125, "strip_ord": 14.5625, "strip_shuf": 12.8125, "retain_ord": 3.109375}, {"ask_first": true, "bare": 8.75, "neutral": 8.6875, "strip_ord": 8.0, "strip_shuf": 9.375, "retain_ord": 4.78125}, {"ask_first": true, "bare": 20.75, "neutral": 20.375, "strip_ord": 20.875, "strip_shuf": 13.9375, "retain_ord": 8.75}, {"ask_first": false, "bare": 10.25, "neutral": 9.0, "strip_ord": 9.8125, "strip_shuf": 8.625, "retain_ord": 4.84375}, {"ask_first": false, "bare": 21.625, "neutral": 21.875, "strip_ord": 22.0, "strip_shuf": 18.75, "retain_ord": 10.375}, {"ask_first": false, "bare": 8.8125, "neutral": 9.375, "strip_ord": 8.0625, "strip_shuf": 6.0625, "retain_ord": 3.625}, {"ask_first": false, "bare": 18.25, "neutral": 19.625, "strip_ord": 25.125, "strip_shuf": 23.375, "retain_ord": 8.0625}, {"ask_first": true, "bare": 8.3125, "neutral": 8.5, "strip_ord": 11.125, "strip_shuf": 10.8125, "retain_ord": 3.375}, {"ask_first": true, "bare": 25.5, "neutral": 25.875, "strip_ord": 26.5, "strip_shuf": 19.375, "retain_ord": 9.875}, {"ask_first": false, "bare": 24.5, "neutral": 21.25, "strip_ord": 20.0, "strip_shuf": 14.5625, "retain_ord": 10.5}, {"ask_first": false, "bare": 12.75, "neutral": 13.0625, "strip_ord": 13.5625, "strip_shuf": 13.0625, "retain_ord": 3.53125}, {"ask_first": false, "bare": 11.5, "neutral": 11.875, "strip_ord": 12.25, "strip_shuf": 12.5, "retain_ord": 3.984375}, {"ask_first": false, "bare": 11.0, "neutral": 11.3125, "strip_ord": 13.5625, "strip_shuf": 10.1875, "retain_ord": 6.03125}, {"ask_first": true, "bare": 13.0, "neutral": 11.5, "strip_ord": 14.6875, "strip_shuf": 11.375, "retain_ord": 4.25}, {"ask_first": false, "bare": 23.25, "neutral": 21.875, "strip_ord": 24.125, "strip_shuf": 17.75, "retain_ord": 7.53125}, {"ask_first": true, "bare": 23.375, "neutral": 23.875, "strip_ord": 18.0, "strip_shuf": 23.125, "retain_ord": 8.375}, {"ask_first": false, "bare": 22.5, "neutral": 20.75, "strip_ord": 22.625, "strip_shuf": 17.0, "retain_ord": 9.25}, {"ask_first": true, "bare": 7.15625, "neutral": 8.125, "strip_ord": 5.4375, "strip_shuf": 6.6875, "retain_ord": 2.75}, {"ask_first": false, "bare": 23.375, "neutral": 23.625, "strip_ord": 24.125, "strip_shuf": 24.0, "retain_ord": 4.6875}, {"ask_first": true, "bare": 12.1875, "neutral": 11.625, "strip_ord": 12.4375, "strip_shuf": 11.25, "retain_ord": 3.015625}, {"ask_first": true, "bare": 9.0625, "neutral": 10.375, "strip_ord": 6.71875, "strip_shuf": 7.78125, "retain_ord": 3.203125}, {"ask_first": false, "bare": 11.6875, "neutral": 12.3125, "strip_ord": 9.4375, "strip_shuf": 8.8125, "retain_ord": 5.09375}, {"ask_first": false, "bare": 11.8125, "neutral": 11.375, "strip_ord": 11.0, "strip_shuf": 12.5, "retain_ord": 5.5625}, {"ask_first": false, "bare": 10.75, "neutral": 10.5, "strip_ord": 10.0625, "strip_shuf": 7.65625, "retain_ord": 4.21875}, {"ask_first": false, "bare": 21.25, "neutral": 19.75, "strip_ord": 21.75, "strip_shuf": 22.25, "retain_ord": 7.1875}, {"ask_first": true, "bare": 24.375, "neutral": 24.625, "strip_ord": 29.5, "strip_shuf": 14.4375, "retain_ord": 9.5}, {"ask_first": true, "bare": 22.375, "neutral": 19.75, "strip_ord": 22.0, "strip_shuf": 22.5, "retain_ord": 8.75}, {"ask_first": true, "bare": 10.375, "neutral": 12.5, "strip_ord": 7.15625, "strip_shuf": 9.6875, "retain_ord": 3.75}, {"ask_first": true, "bare": 23.75, "neutral": 24.25, "strip_ord": 25.25, "strip_shuf": 24.0, "retain_ord": 11.1875}, {"ask_first": false, "bare": 26.875, "neutral": 27.375, "strip_ord": 32.0, "strip_shuf": 30.625, "retain_ord": 8.4375}, {"ask_first": false, "bare": 12.5, "neutral": 12.9375, "strip_ord": 12.4375, "strip_shuf": 13.0, "retain_ord": 3.546875}, {"ask_first": true, "bare": 8.9375, "neutral": 9.125, "strip_ord": 8.3125, "strip_shuf": 8.9375, "retain_ord": 3.25}, {"ask_first": false, "bare": 10.25, "neutral": 9.125, "strip_ord": 12.125, "strip_shuf": 10.125, "retain_ord": 5.1875}, {"ask_first": true, "bare": 15.6875, "neutral": 14.0, "strip_ord": 10.125, "strip_shuf": 16.25, "retain_ord": 5.125}, {"ask_first": true, "bare": 17.125, "neutral": 13.375, "strip_ord": 16.125, "strip_shuf": 16.25, "retain_ord": 8.0625}, {"ask_first": false, "bare": 10.6875, "neutral": 9.9375, "strip_ord": 10.1875, "strip_shuf": 9.875, "retain_ord": 4.96875}, {"ask_first": false, "bare": 20.75, "neutral": 18.5, "strip_ord": 22.625, "strip_shuf": 24.0, "retain_ord": 9.125}, {"ask_first": true, "bare": 10.125, "neutral": 10.4375, "strip_ord": 8.5625, "strip_shuf": 6.84375, "retain_ord": 3.765625}, {"ask_first": true, "bare": 24.625, "neutral": 22.125, "strip_ord": 17.875, "strip_shuf": 21.0, "retain_ord": 12.625}, {"ask_first": true, "bare": 11.0625, "neutral": 11.5, "strip_ord": 12.6875, "strip_shuf": 10.875, "retain_ord": 4.71875}, {"ask_first": true, "bare": 9.625, "neutral": 9.6875, "strip_ord": 8.5, "strip_shuf": 9.0, "retain_ord": 3.609375}, {"ask_first": true, "bare": 9.0625, "neutral": 9.625, "strip_ord": 8.6875, "strip_shuf": 8.1875, "retain_ord": 3.625}, {"ask_first": true, "bare": 16.5, "neutral": 14.9375, "strip_ord": 15.6875, "strip_shuf": 13.4375, "retain_ord": 7.75}, {"ask_first": false, "bare": 9.5625, "neutral": 9.25, "strip_ord": 8.9375, "strip_shuf": 7.375, "retain_ord": 5.0625}, {"ask_first": true, "bare": 21.5, "neutral": 16.25, "strip_ord": 18.875, "strip_shuf": 19.375, "retain_ord": 8.625}, {"ask_first": true, "bare": 24.625, "neutral": 26.25, "strip_ord": 18.875, "strip_shuf": 21.375, "retain_ord": 9.5625}, {"ask_first": false, "bare": 21.375, "neutral": 19.75, "strip_ord": 23.875, "strip_shuf": 18.875, "retain_ord": 9.1875}, {"ask_first": true, "bare": 11.0, "neutral": 10.5625, "strip_ord": 7.375, "strip_shuf": 11.4375, "retain_ord": 3.796875}, {"ask_first": true, "bare": 24.25, "neutral": 25.875, "strip_ord": 22.625, "strip_shuf": 22.25, "retain_ord": 12.8125}, {"ask_first": true, "bare": 11.6875, "neutral": 11.1875, "strip_ord": 11.625, "strip_shuf": 11.125, "retain_ord": 3.703125}, {"ask_first": true, "bare": 8.9375, "neutral": 9.25, "strip_ord": 5.53125, "strip_shuf": 7.5625, "retain_ord": 3.625}, {"ask_first": false, "bare": 12.75, "neutral": 14.3125, "strip_ord": 10.1875, "strip_shuf": 10.125, "retain_ord": 4.3125}, {"ask_first": false, "bare": 13.125, "neutral": 11.0, "strip_ord": 14.0625, "strip_shuf": 8.0625, "retain_ord": 4.875}, {"ask_first": false, "bare": 10.4375, "neutral": 12.1875, "strip_ord": 10.375, "strip_shuf": 9.9375, "retain_ord": 4.1875}, {"ask_first": true, "bare": 19.0, "neutral": 17.375, "strip_ord": 21.0, "strip_shuf": 9.625, "retain_ord": 7.34375}, {"ask_first": false, "bare": 9.75, "neutral": 9.5, "strip_ord": 10.5625, "strip_shuf": 7.40625, "retain_ord": 4.0}, {"ask_first": false, "bare": 20.25, "neutral": 20.125, "strip_ord": 25.75, "strip_shuf": 24.5, "retain_ord": 9.0}, {"ask_first": false, "bare": 12.25, "neutral": 11.75, "strip_ord": 11.3125, "strip_shuf": 10.5, "retain_ord": 4.1875}, {"ask_first": true, "bare": 23.625, "neutral": 21.5, "strip_ord": 17.375, "strip_shuf": 15.5625, "retain_ord": 12.125}, {"ask_first": true, "bare": 13.0625, "neutral": 12.875, "strip_ord": 10.3125, "strip_shuf": 12.0625, "retain_ord": 3.96875}, {"ask_first": true, "bare": 9.1875, "neutral": 9.375, "strip_ord": 8.375, "strip_shuf": 7.8125, "retain_ord": 3.328125}, {"ask_first": false, "bare": 10.875, "neutral": 10.3125, "strip_ord": 11.0625, "strip_shuf": 10.75, "retain_ord": 4.5}, {"ask_first": true, "bare": 19.0, "neutral": 20.5, "strip_ord": 16.875, "strip_shuf": 16.5, "retain_ord": 7.34375}, {"ask_first": true, "bare": 14.5, "neutral": 11.8125, "strip_ord": 11.6875, "strip_shuf": 11.75, "retain_ord": 5.25}, {"ask_first": true, "bare": 18.0, "neutral": 17.125, "strip_ord": 7.65625, "strip_shuf": 16.0, "retain_ord": 10.625}, {"ask_first": false, "bare": 9.5, "neutral": 8.875, "strip_ord": 8.4375, "strip_shuf": 7.90625, "retain_ord": 4.1875}, {"ask_first": false, "bare": 19.25, "neutral": 18.125, "strip_ord": 24.25, "strip_shuf": 17.125, "retain_ord": 8.5625}, {"ask_first": false, "bare": 11.9375, "neutral": 11.6875, "strip_ord": 11.75, "strip_shuf": 10.125, "retain_ord": 5.15625}, {"ask_first": true, "bare": 20.75, "neutral": 19.125, "strip_ord": 20.875, "strip_shuf": 19.75, "retain_ord": 8.1875}, {"ask_first": true, "bare": 10.4375, "neutral": 10.4375, "strip_ord": 8.75, "strip_shuf": 8.8125, "retain_ord": 3.453125}, {"ask_first": true, "bare": 8.5625, "neutral": 9.5625, "strip_ord": 7.71875, "strip_shuf": 8.8125, "retain_ord": 3.203125}, {"ask_first": false, "bare": 12.3125, "neutral": 12.0625, "strip_ord": 10.5, "strip_shuf": 7.78125, "retain_ord": 4.09375}]}